{
    "date": "March 29, 1984",
    "day": "Thursday",
    "venue": "Marin County Veteran's Memorial Auditorium",
    "city": "San Rafael",
    "region": "CA",
    "country": "USA",
    "setlist": {
        "setOne": [
            "Walkin' The Dog",
            "Bertha",
            "Promised Land",
            "It Must Have Been The Roses",
            "Little Red Rooster",
            "Bird Song",
            "My Brother Esau",
            "Might As Well"
        ],
        "setTwo": [
            "Shakedown Street",
            "Estimated Prophet",
            "Eyes Of The World",
            "Drums",
            "Spanish Jam",
            "The Other One",
            "Wharf Rat",
            "Sugar Magnolia"
        ],
        "encore": [
            "Day Job"
        ]
    }
}