{
    "date": "October 25, 1979",
    "day": "Thursday",
    "venue": "New Haven Coliseum",
    "city": "New Haven",
    "region": "CT",
    "country": "USA",
    "setlist": {
        "setOne": [
            "Don't Ease Me In",
            "Cassidy",
            "Peggy-O",
            "El Paso",
            "Brown-Eyed Women",
            "It's All Over Now",
            "Tennessee Jed",
            "Looks Like Rain",
            "Deal"
        ],
        "setTwo": [
            "Shakedown Street",
            "Passenger",
            "Friend Of The Devil",
            "Estimated Prophet",
            "Eyes Of The World",
            "Drums",
            "Stella Blue",
            "Good Lovin'"
        ],
        "encore": [
            "U.S. Blues"
        ]
    }
}